Metadata-Version: 2.1
Name: abnativ
Version: 2.0.4
Summary: AbNatiV: a VQ-VAE-based assessment of the nativeness of antibodies.
Author-email: Aubin Ramon <ar2033@cam.ac.uk>
License: MIT License
Requires-Python: >=3.8
License-File: LICENSE
Requires-Dist: biopython
Requires-Dist: brewer2mpl
Requires-Dist: chroma
Requires-Dist: einops
Requires-Dist: freesasa
Requires-Dist: immunebuilder
Requires-Dist: matplotlib
Requires-Dist: mlflow
Requires-Dist: numpy
Requires-Dist: pandas
Requires-Dist: paretoset
Requires-Dist: pytorch-lightning
Requires-Dist: PyYAML
Requires-Dist: torch
Requires-Dist: python-parallel
Requires-Dist: protein-topmodel
Requires-Dist: scipy
Requires-Dist: seaborn
Requires-Dist: tqdm
Requires-Dist: wandb
